LICENSE
MANIFEST.in
README.rst
setup.py
PolyPasswordHasher.egg-info/PKG-INFO
PolyPasswordHasher.egg-info/SOURCES.txt
PolyPasswordHasher.egg-info/dependency_links.txt
PolyPasswordHasher.egg-info/requires.txt
PolyPasswordHasher.egg-info/top_level.txt
polypasswordhasher/__init__.py
polypasswordhasher/pph.py
polypasswordhasher/shamirsecret.py
polypasswordhasher/tests/__init__.py
polypasswordhasher/tests/test_polypasswordhasher.py
polypasswordhasher/tests/test_shamirsecret.py